arcana/core/__init__.py
arcana/core/_version.py
arcana/core/exceptions.py
arcana/core/mark.py
arcana/core/analysis/__init__.py
arcana/core/analysis/make.py
arcana/core/analysis/mark.py
arcana/core/analysis/pipeline.py
arcana/core/analysis/salience.py
arcana/core/analysis/spec.py
arcana/core/analysis/tasks/__init__.py
arcana/core/analysis/tasks/shell.py
arcana/core/analysis/tasks/utils.py
arcana/core/analysis/tasks/tests/test_shell.py
arcana/core/analysis/tests/test_analysis.py
arcana/core/analysis/tests/test_pipeline.py
arcana/core/cli/__init__.py
arcana/core/cli/apply.py
arcana/core/cli/base.py
arcana/core/cli/dataset.py
arcana/core/cli/deploy.py
arcana/core/cli/derive.py
arcana/core/cli/ext.py
arcana/core/cli/store.py
arcana/core/cli/tests/test_cli_apply.py
arcana/core/cli/tests/test_cli_dataset.py
arcana/core/cli/tests/test_cli_deploy.py
arcana/core/cli/tests/test_cli_derive.py
arcana/core/cli/tests/test_cli_ext.py
arcana/core/cli/tests/test_cli_store.py
arcana/core/data/__init__.py
arcana/core/data/column.py
arcana/core/data/row.py
arcana/core/data/set.py
arcana/core/data/space.py
arcana/core/data/store.py
arcana/core/data/tests/test_clinical_space.py
arcana/core/data/tests/test_data_column.py
arcana/core/data/tests/test_dataset.py
arcana/core/deploy/__init__.py
arcana/core/deploy/command/__init__.py
arcana/core/deploy/command/base.py
arcana/core/deploy/command/components.py
arcana/core/deploy/command/entrypoint_opts.py
arcana/core/deploy/command/tests/test_deploy_command.py
arcana/core/deploy/image/__init__.py
arcana/core/deploy/image/app.py
arcana/core/deploy/image/base.py
arcana/core/deploy/image/components.py
arcana/core/deploy/image/metapackage.py
arcana/core/deploy/tests/test_licenses.py
arcana/core/utils/__init__.py
arcana/core/utils/misc.py
arcana/core/utils/packaging.py
arcana/core/utils/serialize.py
arcana/core/utils/testing/__init__.py
arcana/core/utils/testing/tasks.py
arcana/core/utils/testing/data/__init__.py
arcana_core-0.8.6.dist-info/entry_points.txt
arcana_core-0.8.6.dist-info/LICENSE
arcana_core-0.8.6.dist-info/WHEEL
arcana_core-0.8.6.dist-info/METADATA
arcana_core-0.8.6.dist-info/RECORD
