Metadata-Version: 2.1
Name: arcana-core
Version: 0.8.6
Summary: Abstraction of Repository-Centric ANAlysis (Arcana): A rramework for analysing on file-based datasets "in-place" (i.e. without manual download)
Keywords: arcana
Author-email: "Thomas G. Close" <tom.g.close@gmail.com>
Maintainer-email: "Thomas G. Close" <tom.g.close@gmail.com>
Requires-Python: >=3.8
Classifier: Development Status :: 4 - Beta
Classifier: Environment :: Console
Classifier: Intended Audience :: Science/Research
Classifier: License :: OSI Approved :: Apache Software License
Classifier: Operating System :: MacOS :: MacOS X
Classifier: Operating System :: POSIX :: Linux
Classifier: Programming Language :: Python :: 3
Classifier: Topic :: Scientific/Engineering
Requires-Dist: docker>=5.0.2
Requires-Dist: attrs>=22.1.0
Requires-Dist: importlib-metadata>=1.4
Requires-Dist: click>=7.1.2
Requires-Dist: click-option-group>=0.5.5
Requires-Dist: PyYAML>=6.0
Requires-Dist: build >=0.9
Requires-Dist: flit_scm >=1.7.0
Requires-Dist: deepdiff>=3.3
Requires-Dist: pydra>=0.20
Requires-Dist: neurodocker>=0.9.1
Requires-Dist: fileformats-core >=0.1
Requires-Dist: fileformats-common >=0.1
Requires-Dist: pre-commit ; extra == "dev"
Requires-Dist: packaging ; extra == "doc"
Requires-Dist: docutils>=0.10 ; extra == "doc"
Requires-Dist: mock>1.0 ; extra == "doc"
Requires-Dist: sphinx >=2.1.2 ; extra == "doc"
Requires-Dist: sphinx-argparse>=0.2.0 ; extra == "doc"
Requires-Dist: sphinx-click>=3.1 ; extra == "doc"
Requires-Dist: furo>=2022.2.14.1 ; extra == "doc"
Requires-Dist: numpydoc>=0.6.0 ; extra == "doc"
Requires-Dist: pytest>=5.4.3 ; extra == "test"
Requires-Dist: pytest-env>=0.6.2 ; extra == "test"
Requires-Dist: pytest-cov>=2.12.1 ; extra == "test"
Requires-Dist: codecov ; extra == "test"
Project-URL: documentation, https://arcana.readthedocs.io
Project-URL: homepage, https://arcana.readthedocs.io
Project-URL: repository, https://github.com/ArcanaFramework/arcana.git
Provides-Extra: dev
Provides-Extra: doc
Provides-Extra: test
